{
  "meta-version": "1",
  "license": "Artistic-2.0",
  "description": "",
  "tags": [
  ],
  "build-depends": [
  ],
  "name": "release-test",
  "resources": [
  ],
  "source-url": "https://github.com/gfldex/raku-release-test.git",
  "production": true,
  "support": {
    "source": null
  },
  "provides": {
  },
  "auth": "github:gfldex",
  "authors": [
    "Wenzel P. P. Peppmeyer <wenzel.peppmeyer@gmx.de>"
  ],
  "version": "0.0.10",
  "test-depends": [
  ],
  "perl": "6.c",
  "depends": [
    "Test::META"
  ]
}